{
  "合金牌号": "TA18",
  "名义化学成分": "Ti-3AI-2.5V",
  "化学成分（质量分数）": {
    "主要成分": {
      "Ti": "余量",
      "Al": "2.0～3.5",
      "Si": "",
      "V": "1.5~3.0",
      "Mn": "",
      "Ni": "",
      "Cu": "",
      "Zr": "",
      "Nb": "",
      "Mo": "",
      "Ru": "",
      "Pd": "",
      "Sn": "",
      "Ta": "",
      "Nd": ""
    },
    "杂质，不大于": {
      "Fe": "0.25",
      "C": "0.08",
      "N": "0.05",
      "H": "0.015",
      "O": "0.12",
      "其他元素-单一": "0.10",
      "其他元素-总和": "0.30"
    }
  }
}